README.md
setup.cfg
setup.py
sort_pack/__init__.py
sort_pack/__main__.py
sort_pack/about.py
sort_pack/random_list.py
sort_pack/sort_counting.py
sort_pack/test.py
sort_pack.egg-info/PKG-INFO
sort_pack.egg-info/SOURCES.txt
sort_pack.egg-info/dependency_links.txt
sort_pack.egg-info/entry_points.txt
sort_pack.egg-info/top_level.txt