Metadata-Version: 2.1
Name: sort-pack
Version: 0.2
Summary: Merge sort
Author: Tetyshkin Maxim
Author-email: maksimtetuskin1267@mail.ru
License: MIT License
Requires-Python: >=3.5
